{
  "project_info": {
    "project_number": "719339414670",
    "project_id": "mega-neqabty",
    "storage_bucket": "mega-neqabty.appspot.com"
  },
  "client": [
    {
      "client_info": {
        "mobilesdk_app_id": "1:719339414670:android:cd1c5639fd87006df695df",
        "android_client_info": {
          "package_name": "com.neqabty.healthcare"
        }
      },
      "oauth_client": [
        {
          "client_id": "719339414670-3p7u3ko1mtoao1a2nka6fh1rtoc4qkov.apps.googleusercontent.com",
          "client_type": 3
        }
      ],
      "api_key": [
        {
          "current_key": "AIzaSyDcQCxCCtFheybIZsXqxuBtbQKKVnPeKyo"
        }
      ],
      "services": {
        "appinvite_service": {
          "other_platform_oauth_client": [
            {
              "client_id": "719339414670-3p7u3ko1mtoao1a2nka6fh1rtoc4qkov.apps.googleusercontent.com",
              "client_type": 3
            }
          ]
        }
      }
    }
  ],
  "configuration_version": "1"
}